macscribe/__init__.py
macscribe/cli.py
macscribe/clipboard.py
macscribe/downloader.py
macscribe/transcriber.py
macscribe-0.1.2.dist-info/METADATA
macscribe-0.1.2.dist-info/WHEEL
macscribe-0.1.2.dist-info/entry_points.txt
macscribe-0.1.2.dist-info/licenses/LICENSE
macscribe-0.1.2.dist-info/RECORD
