Metadata-Version: 2.4
Name: macscribe
Version: 0.1.2
Summary: Add your description here
Author-email: Kasper Junge <kasperjuunge@gmail.com>
License-File: LICENSE
Requires-Python: >=3.12
Requires-Dist: mlx-whisper>=0.4.1
Requires-Dist: typer>=0.15.1
Requires-Dist: yt-dlp>=2025.1.12
Provides-Extra: test
Requires-Dist: pytest-mock>=3.10.0; extra == 'test'
Requires-Dist: pytest>=7.0.0; extra == 'test'
